tests/__init__.py
utils/__init__.py
utils/debug_demo.py
utils/dict_combine.py
utils/monitor_server.py
utils/python_doc.py
utils/regex.py
utils/strconvert.py
python_demo-0.0.3.dist-info/METADATA
python_demo-0.0.3.dist-info/WHEEL
python_demo-0.0.3.dist-info/entry_points.txt
python_demo-0.0.3.dist-info/top_level.txt
python_demo-0.0.3.dist-info/RECORD
