Metadata-Version: 2.1
Name: python-demo
Version: 0.0.3
Summary: python scripts demos
Home-page: https://github.com/dennycn/script-langs
Author: wuqifu
Author-email: wuqifu@gmail.com
License: BSD-3-Clause
Project-URL: Documentation, https://github.com/dennycn/script-langs
Project-URL: Code, https://github.com/dennycn/script-langs
Project-URL: Issue tracker, https://github.com/dennycn/script-langs/issues
Keywords: python-demo
Platform: UNKNOWN
Classifier: Programming Language :: Python
Classifier: Programming Language :: Python :: 3.5
Classifier: Programming Language :: Python :: 3.6
Requires-Python: >=3
Requires-Dist: flask
